eurogastp/__init__.py
eurogastp/entsog.py
eurogastp/gie.py
eurogastp/topo/Dataproviders.csv
eurogastp/topo/ENTSOG_TP_Network_v3.xlsx
eurogastp/topo/ENTSOG_TP_Network_v4.xlsx
eurogastp-0.1.3.dist-info/METADATA
eurogastp-0.1.3.dist-info/WHEEL
eurogastp-0.1.3.dist-info/licenses/LICENSE.txt
eurogastp-0.1.3.dist-info/licenses/Notice.txt
eurogastp-0.1.3.dist-info/RECORD
