Metadata-Version: 2.1
Name: eurogastp
Version: 0.1.3
Summary: Python tools for analyzing the European gas system
Project-URL: Source, https://github.com/proggy/eurogastp
Project-URL: Homepage, https://github.com/proggy/eurogastp
Project-URL: Bug Tracker, https://github.com/proggy/eurogastp/issues
Author-email: Daniel Jung <proggy-contact@mailbox.org>
Maintainer-email: Daniel Jung <proggy-contact@mailbox.org>
License-File: LICENSE.txt
License-File: Notice.txt
Classifier: License :: OSI Approved :: European Union Public Licence 1.2 (EUPL 1.2)
Classifier: Operating System :: OS Independent
Classifier: Programming Language :: Python :: 3
Requires-Python: >=3.7
Requires-Dist: numpy
Requires-Dist: pandas
